{
  "type": "Feature",
  "id": "PathCellObject",
  "geometry": {
    "type": "Polygon",
    "coordinates": [
      [
        [12398.46, 25769.31],
        [12395, 25774.12],
        [12396.2, 25781.99],
        [12397.92, 25785.59],
        [12402.32, 25789.66],
        [12407.82, 25792],
        [12419.81, 25791.84],
        [12423.45, 25790.21],
        [12425.58, 25786.85],
        [12425.98, 25780.89],
        [12425.33, 25779],
        [12423.54, 25778.11],
        [12419.54, 25778],
        [12414.31, 25775.15],
        [12405.14, 25771.23],
        [12398.46, 25769.31]
      ]
    ]
  },
  "nucleusGeometry": {
    "type": "Polygon",
    "coordinates": [
      [
        [12405.49, 25772.41],
        [12402, 25774.33],
        [12401.65, 25776.3],
        [12402.25, 25780.25],
        [12406.32, 25784.65],
        [12410.05, 25786],
        [12418.04, 25785.79],
        [12419.64, 25784.6],
        [12419.67, 25782.6],
        [12418.7, 25780.85],
        [12413.39, 25778.08],
        [12411.48, 25778.67],
        [12408.2, 25776.53],
        [12405.49, 25772.41]
      ]
    ]
  },
  "properties": {
    "classification": {
      "name": "Positive",
      "colorRGB": -8342656
    },
    "isLocked": false,
    "measurements": [
      {
        "name": "Nucleus: Area",
        "value": 29.063495635986328
      },
      {
        "name": "Nucleus: Perimeter",
        "value": 23.168228149414062
      },
      {
        "name": "Nucleus: Circularity",
        "value": 0.6804121136665344
      },
      {
        "name": "Nucleus: Max caliper",
        "value": 9.266728401184082
      },
      {
        "name": "Nucleus: Min caliper",
        "value": 4.480273723602295
      },
      {
        "name": "Nucleus: Eccentricity",
        "value": 0.8892316222190857
      },
      {
        "name": "Nucleus: Hematoxylin OD mean",
        "value": 0.2687879800796509
      },
      {
        "name": "Nucleus: Hematoxylin OD sum",
        "value": 38.16789245605469
      },
      {
        "name": "Nucleus: Hematoxylin OD std dev",
        "value": 0.21968740224838257
      },
      {
        "name": "Nucleus: Hematoxylin OD max",
        "value": 0.7002618908882141
      },
      {
        "name": "Nucleus: Hematoxylin OD min",
        "value": -0.2136230170726776
      },
      {
        "name": "Nucleus: Hematoxylin OD range",
        "value": 0.9138848781585693
      },
      {
        "name": "Nucleus: DAB OD mean",
        "value": 0.6697262525558472
      },
      {
        "name": "Nucleus: DAB OD sum",
        "value": 95.10112762451172
      },
      {
        "name": "Nucleus: DAB OD std dev",
        "value": 0.5128406286239624
      },
      {
        "name": "Nucleus: DAB OD max",
        "value": 2.1314542293548584
      },
      {
        "name": "Nucleus: DAB OD min",
        "value": -0.11624142527580261
      },
      {
        "name": "Nucleus: DAB OD range",
        "value": 2.2476956844329834
      },
      {
        "name": "Cell: Area",
        "value": 101.8252944946289
      },
      {
        "name": "Cell: Perimeter",
        "value": 39.551631927490234
      },
      {
        "name": "Cell: Circularity",
        "value": 0.8179687857627869
      },
      {
        "name": "Cell: Max caliper",
        "value": 15.044865608215332
      },
      {
        "name": "Cell: Min caliper",
        "value": 8.51326847076416
      },
      {
        "name": "Cell: Eccentricity",
        "value": 0.8341825604438782
      },
      {
        "name": "Cell: Hematoxylin OD mean",
        "value": 0.21319004893302917
      },
      {
        "name": "Cell: Hematoxylin OD std dev",
        "value": 0.18050168454647064
      },
      {
        "name": "Cell: Hematoxylin OD max",
        "value": 0.7002618908882141
      },
      {
        "name": "Cell: Hematoxylin OD min",
        "value": -0.2136230170726776
      },
      {
        "name": "Cell: DAB OD mean",
        "value": 0.602374255657196
      },
      {
        "name": "Cell: DAB OD std dev",
        "value": 0.5254316329956055
      },
      {
        "name": "Cell: DAB OD max",
        "value": 2.1314542293548584
      },
      {
        "name": "Cell: DAB OD min",
        "value": -0.11624142527580261
      },
      {
        "name": "Cytoplasm: Hematoxylin OD mean",
        "value": 0.19082489609718323
      },
      {
        "name": "Cytoplasm: Hematoxylin OD std dev",
        "value": 0.15698158740997314
      },
      {
        "name": "Cytoplasm: Hematoxylin OD max",
        "value": 0.6411207318305969
      },
      {
        "name": "Cytoplasm: Hematoxylin OD min",
        "value": -0.11322179436683655
      },
      {
        "name": "Cytoplasm: DAB OD mean",
        "value": 0.5752808451652527
      },
      {
        "name": "Cytoplasm: DAB OD std dev",
        "value": 0.5287089943885803
      },
      {
        "name": "Cytoplasm: DAB OD max",
        "value": 1.8374226093292236
      },
      {
        "name": "Cytoplasm: DAB OD min",
        "value": -0.06286130100488663
      },
      {
        "name": "Nucleus/Cell area ratio",
        "value": 0.28121691942214966
      }
    ]
  }
}