{
  "type": "Feature",
  "id": "PathCellObject",
  "geometry": {
    "type": "Polygon",
    "coordinates": [
      [
        [12065.87, 24837],
        [12061.87, 24837.06],
        [12058.49, 24839.17],
        [12055, 24844],
        [12048.32, 24848.35],
        [12047, 24852.1],
        [12047.05, 24856.1],
        [12052.25, 24864.58],
        [12057.74, 24866.95],
        [12061.7, 24866.65],
        [12066.45, 24863.09],
        [12070.99, 24852.03],
        [12071.83, 24844.16],
        [12069.16, 24838.82],
        [12065.87, 24837]
      ]
    ]
  },
  "nucleusGeometry": {
    "type": "Polygon",
    "coordinates": [
      [
        [12064.55, 24843.33],
        [12062.67, 24844],
        [12061.04, 24847.63],
        [12056.32, 24851.34],
        [12054.41, 24851.92],
        [12053.08, 24853.42],
        [12054.56, 24857.12],
        [12057.21, 24860.11],
        [12059, 24861],
        [12060.71, 24859.96],
        [12063.63, 24854.73],
        [12065, 24850.97],
        [12065.33, 24845],
        [12064.55, 24843.33]
      ]
    ]
  },
  "properties": {
    "classification": {
      "name": "Negative",
      "colorRGB": -9408287
    },
    "isLocked": false,
    "measurements": [
      {
        "name": "Nucleus: Area",
        "value": 22.879772186279297
      },
      {
        "name": "Nucleus: Perimeter",
        "value": 20.81182289123535
      },
      {
        "name": "Nucleus: Circularity",
        "value": 0.6638062596321106
      },
      {
        "name": "Nucleus: Max caliper",
        "value": 8.405949592590332
      },
      {
        "name": "Nucleus: Min caliper",
        "value": 4.536180019378662
      },
      {
        "name": "Nucleus: Eccentricity",
        "value": 0.8584331274032593
      },
      {
        "name": "Nucleus: Hematoxylin OD mean",
        "value": 0.258394718170166
      },
      {
        "name": "Nucleus: Hematoxylin OD sum",
        "value": 29.715391159057617
      },
      {
        "name": "Nucleus: Hematoxylin OD std dev",
        "value": 0.11375878006219864
      },
      {
        "name": "Nucleus: Hematoxylin OD max",
        "value": 0.4461858570575714
      },
      {
        "name": "Nucleus: Hematoxylin OD min",
        "value": 0.04460318014025688
      },
      {
        "name": "Nucleus: Hematoxylin OD range",
        "value": 0.4015826880931854
      },
      {
        "name": "Nucleus: DAB OD mean",
        "value": 0.0012463205493986607
      },
      {
        "name": "Nucleus: DAB OD sum",
        "value": 0.14332686364650726
      },
      {
        "name": "Nucleus: DAB OD std dev",
        "value": 0.02043222263455391
      },
      {
        "name": "Nucleus: DAB OD max",
        "value": 0.05366821587085724
      },
      {
        "name": "Nucleus: DAB OD min",
        "value": -0.043155230581760406
      },
      {
        "name": "Nucleus: DAB OD range",
        "value": 0.09682344645261765
      },
      {
        "name": "Cell: Area",
        "value": 110.27638244628906
      },
      {
        "name": "Cell: Perimeter",
        "value": 38.94084548950195
      },
      {
        "name": "Cell: Circularity",
        "value": 0.9138640761375427
      },
      {
        "name": "Cell: Max caliper",
        "value": 14.110021591186523
      },
      {
        "name": "Cell: Min caliper",
        "value": 10.354997634887695
      },
      {
        "name": "Cell: Eccentricity",
        "value": 0.7061770558357239
      },
      {
        "name": "Cell: Hematoxylin OD mean",
        "value": 0.07028085738420486
      },
      {
        "name": "Cell: Hematoxylin OD std dev",
        "value": 0.11445986479520798
      },
      {
        "name": "Cell: Hematoxylin OD max",
        "value": 0.4461858570575714
      },
      {
        "name": "Cell: Hematoxylin OD min",
        "value": -0.011134817264974117
      },
      {
        "name": "Cell: DAB OD mean",
        "value": 0.008290674537420273
      },
      {
        "name": "Cell: DAB OD std dev",
        "value": 0.012911456637084484
      },
      {
        "name": "Cell: DAB OD max",
        "value": 0.05366821587085724
      },
      {
        "name": "Cell: DAB OD min",
        "value": -0.043155230581760406
      },
      {
        "name": "Cytoplasm: Hematoxylin OD mean",
        "value": 0.018773488700389862
      },
      {
        "name": "Cytoplasm: Hematoxylin OD std dev",
        "value": 0.028357461094856262
      },
      {
        "name": "Cytoplasm: Hematoxylin OD max",
        "value": 0.16579535603523254
      },
      {
        "name": "Cytoplasm: Hematoxylin OD min",
        "value": -0.011134817264974117
      },
      {
        "name": "Cytoplasm: DAB OD mean",
        "value": 0.010219485498964787
      },
      {
        "name": "Cytoplasm: DAB OD std dev",
        "value": 0.00902918167412281
      },
      {
        "name": "Cytoplasm: DAB OD max",
        "value": 0.045873869210481644
      },
      {
        "name": "Cytoplasm: DAB OD min",
        "value": -0.02202126570045948
      },
      {
        "name": "Nucleus/Cell area ratio",
        "value": 0.21403276920318604
      }
    ]
  }
}