{
  "type": "Feature",
  "id": "PathCellObject",
  "geometry": {
    "type": "Polygon",
    "coordinates": [
      [
        [12786.06, 24999],
        [12782.07, 24999.19],
        [12776.75, 25001.91],
        [12772.51, 25006.16],
        [12771, 25009.83],
        [12771, 25011.83],
        [12769.66, 25017.68],
        [12765.54, 25022.04],
        [12766.47, 25023.81],
        [12770.15, 25025.23],
        [12773.57, 25027.29],
        [12778.33, 25033.65],
        [12782.29, 25033.94],
        [12785.81, 25032.19],
        [12789.31, 25027.36],
        [12790.86, 25023.69],
        [12791, 25015.69],
        [12791.61, 25013.79],
        [12794.41, 25010.93],
        [12796, 25005.14],
        [12795.59, 25003.19],
        [12793.99, 25001.99],
        [12786.06, 24999]
      ]
    ]
  },
  "nucleusGeometry": {
    "type": "Polygon",
    "coordinates": [
      [
        [12783.85, 25005.23],
        [12780.29, 25007.04],
        [12777.53, 25009.93],
        [12773.37, 25016.73],
        [12773.27, 25018.73],
        [12770.33, 25021.34],
        [12769.75, 25023.26],
        [12770.8, 25024.96],
        [12774.71, 25025.41],
        [12776.26, 25026.67],
        [12782.04, 25027.29],
        [12784.93, 25024.53],
        [12788.87, 25024.97],
        [12790.12, 25023.41],
        [12791, 25019.53],
        [12791.29, 25013.55],
        [12792.47, 25011.93],
        [12791.1, 25008.2],
        [12787.3, 25007.15],
        [12785.82, 25005.55],
        [12783.85, 25005.23]
      ]
    ]
  },
  "properties": {
    "classification": {
      "name": "Positive",
      "colorRGB": -8342656
    },
    "isLocked": false,
    "measurements": [
      {
        "name": "Nucleus: Area",
        "value": 67.19644927978516
      },
      {
        "name": "Nucleus: Perimeter",
        "value": 32.905433654785156
      },
      {
        "name": "Nucleus: Circularity",
        "value": 0.7798677682876587
      },
      {
        "name": "Nucleus: Max caliper",
        "value": 11.952431678771973
      },
      {
        "name": "Nucleus: Min caliper",
        "value": 8.110058784484863
      },
      {
        "name": "Nucleus: Eccentricity",
        "value": 0.7132846713066101
      },
      {
        "name": "Nucleus: Hematoxylin OD mean",
        "value": 0.14801456034183502
      },
      {
        "name": "Nucleus: Hematoxylin OD sum",
        "value": 48.69679260253906
      },
      {
        "name": "Nucleus: Hematoxylin OD std dev",
        "value": 0.10535642504692078
      },
      {
        "name": "Nucleus: Hematoxylin OD max",
        "value": 0.6109058856964111
      },
      {
        "name": "Nucleus: Hematoxylin OD min",
        "value": -0.2038421481847763
      },
      {
        "name": "Nucleus: Hematoxylin OD range",
        "value": 0.8147480487823486
      },
      {
        "name": "Nucleus: DAB OD mean",
        "value": 0.4598765969276428
      },
      {
        "name": "Nucleus: DAB OD sum",
        "value": 151.2993927001953
      },
      {
        "name": "Nucleus: DAB OD std dev",
        "value": 0.4675394296646118
      },
      {
        "name": "Nucleus: DAB OD max",
        "value": 2.012294292449951
      },
      {
        "name": "Nucleus: DAB OD min",
        "value": -0.02981886826455593
      },
      {
        "name": "Nucleus: DAB OD range",
        "value": 2.0421130657196045
      },
      {
        "name": "Cell: Area",
        "value": 137.072509765625
      },
      {
        "name": "Cell: Perimeter",
        "value": 46.547908782958984
      },
      {
        "name": "Cell: Circularity",
        "value": 0.7949867248535156
      },
      {
        "name": "Cell: Max caliper",
        "value": 16.199481964111328
      },
      {
        "name": "Cell: Min caliper",
        "value": 10.936388969421387
      },
      {
        "name": "Cell: Eccentricity",
        "value": 0.7470848560333252
      },
      {
        "name": "Cell: Hematoxylin OD mean",
        "value": 0.164179265499115
      },
      {
        "name": "Cell: Hematoxylin OD std dev",
        "value": 0.13376131653785706
      },
      {
        "name": "Cell: Hematoxylin OD max",
        "value": 0.7570977210998535
      },
      {
        "name": "Cell: Hematoxylin OD min",
        "value": -0.2304989993572235
      },
      {
        "name": "Cell: DAB OD mean",
        "value": 0.789113461971283
      },
      {
        "name": "Cell: DAB OD std dev",
        "value": 0.5833759903907776
      },
      {
        "name": "Cell: DAB OD max",
        "value": 2.31392240524292
      },
      {
        "name": "Cell: DAB OD min",
        "value": -0.02981886826455593
      },
      {
        "name": "Cytoplasm: Hematoxylin OD mean",
        "value": 0.17986713349819183
      },
      {
        "name": "Cytoplasm: Hematoxylin OD std dev",
        "value": 0.15503229200839996
      },
      {
        "name": "Cytoplasm: Hematoxylin OD max",
        "value": 0.7570977210998535
      },
      {
        "name": "Cytoplasm: Hematoxylin OD min",
        "value": -0.2304989993572235
      },
      {
        "name": "Cytoplasm: DAB OD mean",
        "value": 1.1086384057998657
      },
      {
        "name": "Cytoplasm: DAB OD std dev",
        "value": 0.5015559792518616
      },
      {
        "name": "Cytoplasm: DAB OD max",
        "value": 2.31392240524292
      },
      {
        "name": "Cytoplasm: DAB OD min",
        "value": 0.010407395660877228
      },
      {
        "name": "Nucleus/Cell area ratio",
        "value": 0.4914362132549286
      }
    ]
  }
}