{
  "type": "Feature",
  "id": "PathCellObject",
  "geometry": {
    "type": "Polygon",
    "coordinates": [
      [
        [10953.28, 24332.36],
        [10948.16, 24335.42],
        [10942.29, 24340.85],
        [10935.15, 24344.27],
        [10932.59, 24351.81],
        [10927.53, 24357.94],
        [10927.97, 24361.87],
        [10929.08, 24363.54],
        [10932.83, 24364.92],
        [10938.07, 24362.04],
        [10941.92, 24363],
        [10961.92, 24363],
        [10967.72, 24361.62],
        [10968.81, 24359.95],
        [10969, 24351.95],
        [10965.82, 24344.65],
        [10962.76, 24339.53],
        [10957.16, 24333.82],
        [10953.28, 24332.36]
      ]
    ]
  },
  "nucleusGeometry": {
    "type": "Polygon",
    "coordinates": [
      [
        [10950.8, 24338.24],
        [10947.17, 24339.92],
        [10944.47, 24342.87],
        [10937.46, 24346.54],
        [10933.65, 24355.71],
        [10933.34, 24357.69],
        [10936.24, 24360.38],
        [10939.86, 24361.93],
        [10953.86, 24362],
        [10959.72, 24362.86],
        [10962.84, 24357.81],
        [10963, 24353.82],
        [10960.66, 24348.32],
        [10957.6, 24343.19],
        [10952.78, 24338.52],
        [10950.8, 24338.24]
      ]
    ]
  },
  "properties": {
    "classification": {
      "name": "Positive",
      "colorRGB": -8342656
    },
    "isLocked": false,
    "measurements": [
      {
        "name": "Nucleus: Area",
        "value": 106.15390014648438
      },
      {
        "name": "Nucleus: Perimeter",
        "value": 39.3785285949707
      },
      {
        "name": "Nucleus: Circularity",
        "value": 0.8602543473243713
      },
      {
        "name": "Nucleus: Max caliper",
        "value": 13.578631401062012
      },
      {
        "name": "Nucleus: Min caliper",
        "value": 11.032954216003418
      },
      {
        "name": "Nucleus: Eccentricity",
        "value": 0.5877223610877991
      },
      {
        "name": "Nucleus: Hematoxylin OD mean",
        "value": 0.12017093598842621
      },
      {
        "name": "Nucleus: Hematoxylin OD sum",
        "value": 62.48888397216797
      },
      {
        "name": "Nucleus: Hematoxylin OD std dev",
        "value": 0.06204340606927872
      },
      {
        "name": "Nucleus: Hematoxylin OD max",
        "value": 0.3519536852836609
      },
      {
        "name": "Nucleus: Hematoxylin OD min",
        "value": -0.2520740032196045
      },
      {
        "name": "Nucleus: Hematoxylin OD range",
        "value": 0.6040276885032654
      },
      {
        "name": "Nucleus: DAB OD mean",
        "value": 0.2676979899406433
      },
      {
        "name": "Nucleus: DAB OD sum",
        "value": 139.2029571533203
      },
      {
        "name": "Nucleus: DAB OD std dev",
        "value": 0.4136381149291992
      },
      {
        "name": "Nucleus: DAB OD max",
        "value": 1.8089460134506226
      },
      {
        "name": "Nucleus: DAB OD min",
        "value": -0.01799914240837097
      },
      {
        "name": "Nucleus: DAB OD range",
        "value": 1.826945185661316
      },
      {
        "name": "Cell: Area",
        "value": 184.89329528808594
      },
      {
        "name": "Cell: Perimeter",
        "value": 54.55902099609375
      },
      {
        "name": "Cell: Circularity",
        "value": 0.7805449366569519
      },
      {
        "name": "Cell: Max caliper",
        "value": 19.200908660888672
      },
      {
        "name": "Cell: Min caliper",
        "value": 14.138594627380371
      },
      {
        "name": "Cell: Eccentricity",
        "value": 0.7088118195533752
      },
      {
        "name": "Cell: Hematoxylin OD mean",
        "value": 0.11832509934902191
      },
      {
        "name": "Cell: Hematoxylin OD std dev",
        "value": 0.06772913783788681
      },
      {
        "name": "Cell: Hematoxylin OD max",
        "value": 0.4042304754257202
      },
      {
        "name": "Cell: Hematoxylin OD min",
        "value": -0.2520740032196045
      },
      {
        "name": "Cell: DAB OD mean",
        "value": 0.4818524420261383
      },
      {
        "name": "Cell: DAB OD std dev",
        "value": 0.46674999594688416
      },
      {
        "name": "Cell: DAB OD max",
        "value": 1.8089460134506226
      },
      {
        "name": "Cell: DAB OD min",
        "value": -0.0265766941010952
      },
      {
        "name": "Cytoplasm: Hematoxylin OD mean",
        "value": 0.11581244319677353
      },
      {
        "name": "Cytoplasm: Hematoxylin OD std dev",
        "value": 0.07478905469179153
      },
      {
        "name": "Cytoplasm: Hematoxylin OD max",
        "value": 0.4042304754257202
      },
      {
        "name": "Cytoplasm: Hematoxylin OD min",
        "value": -0.08844659477472305
      },
      {
        "name": "Cytoplasm: DAB OD mean",
        "value": 0.7733715772628784
      },
      {
        "name": "Cytoplasm: DAB OD std dev",
        "value": 0.3665001690387726
      },
      {
        "name": "Cytoplasm: DAB OD max",
        "value": 1.5105679035186768
      },
      {
        "name": "Cytoplasm: DAB OD min",
        "value": -0.0265766941010952
      },
      {
        "name": "Nucleus/Cell area ratio",
        "value": 0.5743407607078552
      }
    ]
  }
}