{
  "type": "Feature",
  "id": "PathCellObject",
  "geometry": {
    "type": "Polygon",
    "coordinates": [
      [
        [11243.7, 24947],
        [11235.71, 24947.15],
        [11230.47, 24950.06],
        [11227.03, 24954.93],
        [11223.01, 24963.94],
        [11223, 24969.94],
        [11225.23, 24975.46],
        [11233.67, 24984],
        [11238.95, 24986.79],
        [11248.94, 24987],
        [11252.82, 24987.96],
        [11258.82, 24988],
        [11265.95, 24984.39],
        [11269, 24979.35],
        [11269.57, 24975.43],
        [11271.26, 24974.37],
        [11272.86, 24970.71],
        [11273, 24966.72],
        [11271.95, 24962.9],
        [11268.25, 24958.25],
        [11259.01, 24954.51],
        [11251.33, 24948.16],
        [11245.33, 24948],
        [11243.7, 24947]
      ]
    ]
  },
  "nucleusGeometry": {
    "type": "Polygon",
    "coordinates": [
      [
        [11238.67, 24953],
        [11235.12, 24954.76],
        [11231.85, 24959.75],
        [11229.18, 24965.1],
        [11229.22, 24969.08],
        [11231.12, 24972.56],
        [11238.14, 24979.57],
        [11241.86, 24980.97],
        [11249.82, 24980.62],
        [11253.65, 24981.67],
        [11257.59, 24981.71],
        [11262.69, 24978.62],
        [11262.16, 24972.68],
        [11264.73, 24969.65],
        [11266.72, 24969.42],
        [11266.88, 24967.43],
        [11264.08, 24962.17],
        [11261.37, 24959.27],
        [11259.41, 24958.88],
        [11252.33, 24955.16],
        [11244.4, 24955],
        [11242.62, 24953.41],
        [11238.67, 24953]
      ]
    ]
  },
  "properties": {
    "classification": {
      "name": "Positive",
      "colorRGB": -8342656
    },
    "isLocked": false,
    "measurements": [
      {
        "name": "Nucleus: Area",
        "value": 164.89926147460938
      },
      {
        "name": "Nucleus: Perimeter",
        "value": 49.29933547973633
      },
      {
        "name": "Nucleus: Circularity",
        "value": 0.8526022434234619
      },
      {
        "name": "Nucleus: Max caliper",
        "value": 17.200807571411133
      },
      {
        "name": "Nucleus: Min caliper",
        "value": 12.42243480682373
      },
      {
        "name": "Nucleus: Eccentricity",
        "value": 0.6617257595062256
      },
      {
        "name": "Nucleus: Hematoxylin OD mean",
        "value": 0.14258559048175812
      },
      {
        "name": "Nucleus: Hematoxylin OD sum",
        "value": 113.78329467773438
      },
      {
        "name": "Nucleus: Hematoxylin OD std dev",
        "value": 0.10459917783737183
      },
      {
        "name": "Nucleus: Hematoxylin OD max",
        "value": 0.5596829652786255
      },
      {
        "name": "Nucleus: Hematoxylin OD min",
        "value": -0.3851929306983948
      },
      {
        "name": "Nucleus: Hematoxylin OD range",
        "value": 0.9448758959770203
      },
      {
        "name": "Nucleus: DAB OD mean",
        "value": 0.4202359616756439
      },
      {
        "name": "Nucleus: DAB OD sum",
        "value": 335.3482971191406
      },
      {
        "name": "Nucleus: DAB OD std dev",
        "value": 0.5741208791732788
      },
      {
        "name": "Nucleus: DAB OD max",
        "value": 2.936995267868042
      },
      {
        "name": "Nucleus: DAB OD min",
        "value": -0.02097618393599987
      },
      {
        "name": "Nucleus: DAB OD range",
        "value": 2.9579713344573975
      },
      {
        "name": "Cell: Area",
        "value": 324.02703857421875
      },
      {
        "name": "Cell: Perimeter",
        "value": 66.2464599609375
      },
      {
        "name": "Cell: Circularity",
        "value": 0.9278244376182556
      },
      {
        "name": "Cell: Max caliper",
        "value": 22.83816146850586
      },
      {
        "name": "Cell: Min caliper",
        "value": 18.14965057373047
      },
      {
        "name": "Cell: Eccentricity",
        "value": 0.6320501565933228
      },
      {
        "name": "Cell: Hematoxylin OD mean",
        "value": 0.15615683794021606
      },
      {
        "name": "Cell: Hematoxylin OD std dev",
        "value": 0.15368174016475677
      },
      {
        "name": "Cell: Hematoxylin OD max",
        "value": 0.8100579380989075
      },
      {
        "name": "Cell: Hematoxylin OD min",
        "value": -0.3851929306983948
      },
      {
        "name": "Cell: DAB OD mean",
        "value": 0.7242128252983093
      },
      {
        "name": "Cell: DAB OD std dev",
        "value": 0.5971660017967224
      },
      {
        "name": "Cell: DAB OD max",
        "value": 2.9489428997039795
      },
      {
        "name": "Cell: DAB OD min",
        "value": -0.02097618393599987
      },
      {
        "name": "Cytoplasm: Hematoxylin OD mean",
        "value": 0.1701669991016388
      },
      {
        "name": "Cytoplasm: Hematoxylin OD std dev",
        "value": 0.19065509736537933
      },
      {
        "name": "Cytoplasm: Hematoxylin OD max",
        "value": 0.8100579380989075
      },
      {
        "name": "Cytoplasm: Hematoxylin OD min",
        "value": -0.2668802738189697
      },
      {
        "name": "Cytoplasm: DAB OD mean",
        "value": 1.0380207300186157
      },
      {
        "name": "Cytoplasm: DAB OD std dev",
        "value": 0.4368281960487366
      },
      {
        "name": "Cytoplasm: DAB OD max",
        "value": 2.9489428997039795
      },
      {
        "name": "Cytoplasm: DAB OD min",
        "value": 0.14106640219688416
      },
      {
        "name": "Nucleus/Cell area ratio",
        "value": 0.5087116360664368
      }
    ]
  }
}