{
  "type": "Feature",
  "id": "PathCellObject",
  "geometry": {
    "type": "Polygon",
    "coordinates": [
      [
        [11981.34, 24432],
        [11975.91, 24434.54],
        [11970.37, 24440.26],
        [11968.53, 24443.81],
        [11965.7, 24446.63],
        [11965.1, 24450.51],
        [11967.97, 24457.95],
        [11972.32, 24464.65],
        [11975.01, 24470.01],
        [11980.17, 24473],
        [11986.17, 24472.97],
        [11989.89, 24471.56],
        [11994.79, 24468.11],
        [12000.31, 24465.85],
        [12003.22, 24463.11],
        [12005, 24459.55],
        [12006, 24447.67],
        [12004.84, 24443.84],
        [12000.07, 24440.21],
        [11992.86, 24436.93],
        [11987.33, 24432.22],
        [11981.34, 24432]
      ]
    ]
  },
  "nucleusGeometry": {
    "type": "Polygon",
    "coordinates": [
      [
        [11984.58, 24438],
        [11982.59, 24438.21],
        [11979.28, 24440.39],
        [11975.22, 24444.76],
        [11971.52, 24446.24],
        [11970.55, 24447.99],
        [11972.78, 24453.56],
        [11973, 24455.54],
        [11972, 24459.4],
        [11972.19, 24461.39],
        [11973.35, 24463.02],
        [11982.47, 24467],
        [11984.47, 24466.91],
        [11987.99, 24465.01],
        [11989.44, 24463.63],
        [11996.81, 24460.6],
        [11998.34, 24459.31],
        [11998.33, 24455.37],
        [11999.88, 24449.6],
        [11998.64, 24443.75],
        [11997.83, 24441.92],
        [11994.2, 24440.24],
        [11986.33, 24439],
        [11984.58, 24438]
      ]
    ]
  },
  "properties": {
    "classification": {
      "name": "Positive",
      "colorRGB": -8342656
    },
    "isLocked": false,
    "measurements": [
      {
        "name": "Nucleus: Area",
        "value": 128.41529846191406
      },
      {
        "name": "Nucleus: Perimeter",
        "value": 42.685184478759766
      },
      {
        "name": "Nucleus: Circularity",
        "value": 0.8856707215309143
      },
      {
        "name": "Nucleus: Max caliper",
        "value": 14.673788070678711
      },
      {
        "name": "Nucleus: Min caliper",
        "value": 12.009111404418945
      },
      {
        "name": "Nucleus: Eccentricity",
        "value": 0.5010443329811096
      },
      {
        "name": "Nucleus: Hematoxylin OD mean",
        "value": 0.13096553087234497
      },
      {
        "name": "Nucleus: Hematoxylin OD sum",
        "value": 81.85345458984375
      },
      {
        "name": "Nucleus: Hematoxylin OD std dev",
        "value": 0.10099571943283081
      },
      {
        "name": "Nucleus: Hematoxylin OD max",
        "value": 0.6823424100875854
      },
      {
        "name": "Nucleus: Hematoxylin OD min",
        "value": -0.1203690692782402
      },
      {
        "name": "Nucleus: Hematoxylin OD range",
        "value": 0.8027114868164062
      },
      {
        "name": "Nucleus: DAB OD mean",
        "value": 0.34045514464378357
      },
      {
        "name": "Nucleus: DAB OD sum",
        "value": 212.78445434570312
      },
      {
        "name": "Nucleus: DAB OD std dev",
        "value": 0.41674545407295227
      },
      {
        "name": "Nucleus: DAB OD max",
        "value": 2.182814598083496
      },
      {
        "name": "Nucleus: DAB OD min",
        "value": -0.020114703103899956
      },
      {
        "name": "Nucleus: DAB OD range",
        "value": 2.2029292583465576
      },
      {
        "name": "Cell: Area",
        "value": 249.20401000976562
      },
      {
        "name": "Cell: Perimeter",
        "value": 57.78450012207031
      },
      {
        "name": "Cell: Circularity",
        "value": 0.9378689527511597
      },
      {
        "name": "Cell: Max caliper",
        "value": 18.83916664123535
      },
      {
        "name": "Cell: Min caliper",
        "value": 17.620227813720703
      },
      {
        "name": "Cell: Eccentricity",
        "value": 0.29489123821258545
      },
      {
        "name": "Cell: Hematoxylin OD mean",
        "value": 0.11049512028694153
      },
      {
        "name": "Cell: Hematoxylin OD std dev",
        "value": 0.1093108057975769
      },
      {
        "name": "Cell: Hematoxylin OD max",
        "value": 0.794940710067749
      },
      {
        "name": "Cell: Hematoxylin OD min",
        "value": -0.15625755488872528
      },
      {
        "name": "Cell: DAB OD mean",
        "value": 0.4591262936592102
      },
      {
        "name": "Cell: DAB OD std dev",
        "value": 0.45168423652648926
      },
      {
        "name": "Cell: DAB OD max",
        "value": 2.182814598083496
      },
      {
        "name": "Cell: DAB OD min",
        "value": -0.02706177346408367
      },
      {
        "name": "Cytoplasm: Hematoxylin OD mean",
        "value": 0.08862502872943878
      },
      {
        "name": "Cytoplasm: Hematoxylin OD std dev",
        "value": 0.11362318694591522
      },
      {
        "name": "Cytoplasm: Hematoxylin OD max",
        "value": 0.794940710067749
      },
      {
        "name": "Cytoplasm: Hematoxylin OD min",
        "value": -0.15625755488872528
      },
      {
        "name": "Cytoplasm: DAB OD mean",
        "value": 0.585911750793457
      },
      {
        "name": "Cytoplasm: DAB OD std dev",
        "value": 0.4534473121166229
      },
      {
        "name": "Cytoplasm: DAB OD max",
        "value": 1.7500176429748535
      },
      {
        "name": "Cytoplasm: DAB OD min",
        "value": -0.02706177346408367
      },
      {
        "name": "Nucleus/Cell area ratio",
        "value": 0.5152449607849121
      }
    ]
  }
}