{
  "type": "Feature",
  "id": "PathCellObject",
  "geometry": {
    "type": "Polygon",
    "coordinates": [
      [
        [10993.8, 25303],
        [10987.87, 25303.57],
        [10975.14, 25309.19],
        [10972.28, 25314.45],
        [10972.28, 25322.41],
        [10974.01, 25326.02],
        [10976.67, 25329],
        [10980.11, 25331],
        [10991.84, 25332.97],
        [10995.84, 25333],
        [10999.59, 25331.71],
        [11002.59, 25329.08],
        [11004.66, 25325.67],
        [11003, 25317.88],
        [11002.98, 25309.88],
        [11002.13, 25308.06],
        [10993.8, 25303]
      ]
    ]
  },
  "nucleusGeometry": {
    "type": "Polygon",
    "coordinates": [
      [
        [10990.82, 25309.09],
        [10983.89, 25313.05],
        [10979.94, 25313.53],
        [10978.18, 25317.1],
        [10978, 25319.09],
        [10979.46, 25322.79],
        [10980.87, 25324.2],
        [10986.55, 25326],
        [10990.55, 25326.11],
        [10994.43, 25327],
        [10996.32, 25326.34],
        [10998.8, 25323.2],
        [10999, 25317.28],
        [10998.57, 25313.37],
        [10996.57, 25313.24],
        [10993.33, 25311],
        [10992.74, 25309.64],
        [10990.82, 25309.09]
      ]
    ]
  },
  "properties": {
    "classification": {
      "name": "Positive",
      "colorRGB": -8342656
    },
    "isLocked": false,
    "measurements": [
      {
        "name": "Nucleus: Area",
        "value": 57.096370697021484
      },
      {
        "name": "Nucleus: Perimeter",
        "value": 28.823293685913086
      },
      {
        "name": "Nucleus: Circularity",
        "value": 0.8636367917060852
      },
      {
        "name": "Nucleus: Max caliper",
        "value": 9.762675285339355
      },
      {
        "name": "Nucleus: Min caliper",
        "value": 7.859580039978027
      },
      {
        "name": "Nucleus: Eccentricity",
        "value": 0.6515125632286072
      },
      {
        "name": "Nucleus: Hematoxylin OD mean",
        "value": 0.18863236904144287
      },
      {
        "name": "Nucleus: Hematoxylin OD sum",
        "value": 52.43980026245117
      },
      {
        "name": "Nucleus: Hematoxylin OD std dev",
        "value": 0.09148642420768738
      },
      {
        "name": "Nucleus: Hematoxylin OD max",
        "value": 0.40643972158432007
      },
      {
        "name": "Nucleus: Hematoxylin OD min",
        "value": -0.08784813433885574
      },
      {
        "name": "Nucleus: Hematoxylin OD range",
        "value": 0.4942878484725952
      },
      {
        "name": "Nucleus: DAB OD mean",
        "value": 0.4651179015636444
      },
      {
        "name": "Nucleus: DAB OD sum",
        "value": 129.3027801513672
      },
      {
        "name": "Nucleus: DAB OD std dev",
        "value": 0.3840395212173462
      },
      {
        "name": "Nucleus: DAB OD max",
        "value": 1.3441858291625977
      },
      {
        "name": "Nucleus: DAB OD min",
        "value": -0.006720708683133125
      },
      {
        "name": "Nucleus: DAB OD range",
        "value": 1.350906491279602
      },
      {
        "name": "Cell: Area",
        "value": 159.95228576660156
      },
      {
        "name": "Cell: Perimeter",
        "value": 46.23347473144531
      },
      {
        "name": "Cell: Circularity",
        "value": 0.940345048904419
      },
      {
        "name": "Cell: Max caliper",
        "value": 15.562479972839355
      },
      {
        "name": "Cell: Min caliper",
        "value": 13.587841987609863
      },
      {
        "name": "Cell: Eccentricity",
        "value": 0.4298098385334015
      },
      {
        "name": "Cell: Hematoxylin OD mean",
        "value": 0.12719658017158508
      },
      {
        "name": "Cell: Hematoxylin OD std dev",
        "value": 0.0949486494064331
      },
      {
        "name": "Cell: Hematoxylin OD max",
        "value": 0.40643972158432007
      },
      {
        "name": "Cell: Hematoxylin OD min",
        "value": -0.5046393871307373
      },
      {
        "name": "Cell: DAB OD mean",
        "value": 0.669948399066925
      },
      {
        "name": "Cell: DAB OD std dev",
        "value": 0.48039868474006653
      },
      {
        "name": "Cell: DAB OD max",
        "value": 2.359490394592285
      },
      {
        "name": "Cell: DAB OD min",
        "value": -0.008207512088119984
      },
      {
        "name": "Cytoplasm: Hematoxylin OD mean",
        "value": 0.09303828328847885
      },
      {
        "name": "Cytoplasm: Hematoxylin OD std dev",
        "value": 0.07822882384061813
      },
      {
        "name": "Cytoplasm: Hematoxylin OD max",
        "value": 0.3447553217411041
      },
      {
        "name": "Cytoplasm: Hematoxylin OD min",
        "value": -0.5046393871307373
      },
      {
        "name": "Cytoplasm: DAB OD mean",
        "value": 0.7838340997695923
      },
      {
        "name": "Cytoplasm: DAB OD std dev",
        "value": 0.49103376269340515
      },
      {
        "name": "Cytoplasm: DAB OD max",
        "value": 2.359490394592285
      },
      {
        "name": "Cytoplasm: DAB OD min",
        "value": -0.008207512088119984
      },
      {
        "name": "Nucleus/Cell area ratio",
        "value": 0.3551723062992096
      }
    ]
  }
}