{
  "type": "Feature",
  "id": "PathCellObject",
  "geometry": {
    "type": "Polygon",
    "coordinates": [
      [
        [13105.89, 24506.06],
        [13095.97, 24512.7],
        [13093.56, 24515.89],
        [13092, 24521.59],
        [13098.17, 24526.58],
        [13105.94, 24528.47],
        [13111.06, 24531.53],
        [13115.01, 24531],
        [13122.28, 24527.72],
        [13124.74, 24522.32],
        [13124.68, 24516.37],
        [13123.45, 24514.79],
        [13112.97, 24508.99],
        [13105.89, 24506.06]
      ]
    ]
  },
  "nucleusGeometry": {
    "type": "Polygon",
    "coordinates": [
      [
        [13109.65, 24511.18],
        [13106.97, 24514.03],
        [13100.08, 24517.84],
        [13098.05, 24521.26],
        [13098.59, 24523.18],
        [13103.3, 24526.86],
        [13107.3, 24527],
        [13113.11, 24525.52],
        [13115.06, 24525.97],
        [13116.75, 24524.91],
        [13118.71, 24521.44],
        [13118.74, 24517.48],
        [13116.26, 24514.47],
        [13114.27, 24514.63],
        [13109.65, 24511.18]
      ]
    ]
  },
  "properties": {
    "classification": {
      "name": "Positive",
      "colorRGB": -8342656
    },
    "isLocked": false,
    "measurements": [
      {
        "name": "Nucleus: Area",
        "value": 46.17179489135742
      },
      {
        "name": "Nucleus: Perimeter",
        "value": 26.275487899780273
      },
      {
        "name": "Nucleus: Circularity",
        "value": 0.8403980135917664
      },
      {
        "name": "Nucleus: Max caliper",
        "value": 9.547746658325195
      },
      {
        "name": "Nucleus: Min caliper",
        "value": 6.961483478546143
      },
      {
        "name": "Nucleus: Eccentricity",
        "value": 0.7378936409950256
      },
      {
        "name": "Nucleus: Hematoxylin OD mean",
        "value": 0.12418863922357559
      },
      {
        "name": "Nucleus: Hematoxylin OD sum",
        "value": 28.066633224487305
      },
      {
        "name": "Nucleus: Hematoxylin OD std dev",
        "value": 0.05448300763964653
      },
      {
        "name": "Nucleus: Hematoxylin OD max",
        "value": 0.34318503737449646
      },
      {
        "name": "Nucleus: Hematoxylin OD min",
        "value": -0.00770114129409194
      },
      {
        "name": "Nucleus: Hematoxylin OD range",
        "value": 0.35088616609573364
      },
      {
        "name": "Nucleus: DAB OD mean",
        "value": 0.34423962235450745
      },
      {
        "name": "Nucleus: DAB OD sum",
        "value": 77.79814910888672
      },
      {
        "name": "Nucleus: DAB OD std dev",
        "value": 0.3625481128692627
      },
      {
        "name": "Nucleus: DAB OD max",
        "value": 1.2960035800933838
      },
      {
        "name": "Nucleus: DAB OD min",
        "value": -0.003037410555407405
      },
      {
        "name": "Nucleus: DAB OD range",
        "value": 1.2990410327911377
      },
      {
        "name": "Cell: Area",
        "value": 115.84173583984375
      },
      {
        "name": "Cell: Perimeter",
        "value": 40.736366271972656
      },
      {
        "name": "Cell: Circularity",
        "value": 0.8772237300872803
      },
      {
        "name": "Cell: Max caliper",
        "value": 15.054662704467773
      },
      {
        "name": "Cell: Min caliper",
        "value": 9.95165729522705
      },
      {
        "name": "Cell: Eccentricity",
        "value": 0.7407278418540955
      },
      {
        "name": "Cell: Hematoxylin OD mean",
        "value": 0.09900448471307755
      },
      {
        "name": "Cell: Hematoxylin OD std dev",
        "value": 0.06889669597148895
      },
      {
        "name": "Cell: Hematoxylin OD max",
        "value": 0.34318503737449646
      },
      {
        "name": "Cell: Hematoxylin OD min",
        "value": -0.08405753970146179
      },
      {
        "name": "Cell: DAB OD mean",
        "value": 0.5440070033073425
      },
      {
        "name": "Cell: DAB OD std dev",
        "value": 0.38838252425193787
      },
      {
        "name": "Cell: DAB OD max",
        "value": 1.4359596967697144
      },
      {
        "name": "Cell: DAB OD min",
        "value": -0.003037410555407405
      },
      {
        "name": "Cytoplasm: Hematoxylin OD mean",
        "value": 0.08221504092216492
      },
      {
        "name": "Cytoplasm: Hematoxylin OD std dev",
        "value": 0.07237276434898376
      },
      {
        "name": "Cytoplasm: Hematoxylin OD max",
        "value": 0.3396639823913574
      },
      {
        "name": "Cytoplasm: Hematoxylin OD min",
        "value": -0.08405753970146179
      },
      {
        "name": "Cytoplasm: DAB OD mean",
        "value": 0.6771852374076843
      },
      {
        "name": "Cytoplasm: DAB OD std dev",
        "value": 0.34601888060569763
      },
      {
        "name": "Cytoplasm: DAB OD max",
        "value": 1.4359596967697144
      },
      {
        "name": "Cytoplasm: DAB OD min",
        "value": 0.00809260830283165
      },
      {
        "name": "Nucleus/Cell area ratio",
        "value": 0.3893352746963501
      }
    ]
  }
}