{
  "type": "Feature",
  "id": "PathDetectionObject",
  "geometry": {
    "type": "Polygon",
    "coordinates": [
      [
        [26292.03, 11170.23],
        [26288.24, 11171.72],
        [26285.79, 11174.64],
        [26283.09, 11180.88],
        [26282.48, 11184.83],
        [26284.01, 11188.89],
        [26287.73, 11191.25],
        [26292.03, 11191.55],
        [26295.93, 11190.29],
        [26299.06, 11187.9],
        [26301.18, 11184.66],
        [26302.15, 11180.88],
        [26301.78, 11176.84],
        [26299.58, 11173.33],
        [26296.25, 11170.69],
        [26292.03, 11170.23]
      ]
    ]
  },
  "properties": {
    "classification": {
      "parentClass": {
        "name": "Positive",
        "colorRGB": -8342656
      },
      "name": "Positive",
      "colorRGB": -10451360
    },
    "isLocked": false,
    "measurements": [
      {
        "name": "Area µm^2",
        "value": 65.41255187988281
      },
      {
        "name": "Length µm",
        "value": 29.164852142333984
      },
      {
        "name": "Circularity",
        "value": 0.9663877487182617
      },
      {
        "name": "Solidity",
        "value": 1.0
      },
      {
        "name": "Max diameter µm",
        "value": 10.107744216918945
      },
      {
        "name": "Min diameter µm",
        "value": 8.219230651855469
      },
      {
        "name": "Hematoxylin: Mean",
        "value": 0.12045266479253769
      },
      {
        "name": "Hematoxylin: Median",
        "value": 0.12566466629505157
      },
      {
        "name": "Hematoxylin: Min",
        "value": -0.2764204442501068
      },
      {
        "name": "Hematoxylin: Max",
        "value": 0.3495467007160187
      },
      {
        "name": "Hematoxylin: Std.Dev.",
        "value": 0.07151005417108536
      },
      {
        "name": "DAB: Mean",
        "value": 0.9992624521255493
      },
      {
        "name": "DAB: Median",
        "value": 1.0505964756011963
      },
      {
        "name": "DAB: Min",
        "value": 0.09684573113918304
      },
      {
        "name": "DAB: Max",
        "value": 2.0595009326934814
      },
      {
        "name": "DAB: Std.Dev.",
        "value": 0.26729312539100647
      }
    ]
  }
}