{
  "type": "Feature",
  "id": "PathDetectionObject",
  "geometry": {
    "type": "Polygon",
    "coordinates": [
      [
        [26292.51, 11225.83],
        [26289.37, 11226.76],
        [26287.21, 11229.38],
        [26287.46, 11232.77],
        [26289.15, 11235.35],
        [26295.38, 11238.34],
        [26301.72, 11239.1],
        [26305.37, 11236.9],
        [26304.83, 11232.77],
        [26300.12, 11228.03],
        [26292.51, 11225.83]
      ]
    ]
  },
  "properties": {
    "classification": {
      "parentClass": {
        "name": "Positive",
        "colorRGB": -8342656
      },
      "name": "Positive",
      "colorRGB": -10451360
    },
    "isLocked": false,
    "measurements": [
      {
        "name": "Area µm^2",
        "value": 34.81801223754883
      },
      {
        "name": "Length µm",
        "value": 22.46394920349121
      },
      {
        "name": "Circularity",
        "value": 0.867044985294342
      },
      {
        "name": "Solidity",
        "value": 1.0
      },
      {
        "name": "Max diameter µm",
        "value": 8.923284530639648
      },
      {
        "name": "Min diameter µm",
        "value": 5.093952178955078
      },
      {
        "name": "Hematoxylin: Mean",
        "value": 0.23636390268802643
      },
      {
        "name": "Hematoxylin: Median",
        "value": 0.2493824064731598
      },
      {
        "name": "Hematoxylin: Min",
        "value": 0.013909943401813507
      },
      {
        "name": "Hematoxylin: Max",
        "value": 0.4702814221382141
      },
      {
        "name": "Hematoxylin: Std.Dev.",
        "value": 0.06921369582414627
      },
      {
        "name": "DAB: Mean",
        "value": 0.9264220595359802
      },
      {
        "name": "DAB: Median",
        "value": 0.9898223876953125
      },
      {
        "name": "DAB: Min",
        "value": 0.07373097538948059
      },
      {
        "name": "DAB: Max",
        "value": 1.624747633934021
      },
      {
        "name": "DAB: Std.Dev.",
        "value": 0.30546578764915466
      }
    ]
  }
}