{
  "type": "Feature",
  "id": "PathDetectionObject",
  "geometry": {
    "type": "Polygon",
    "coordinates": [
      [
        [25660.03, 11918.68],
        [25655.59, 11922.36],
        [25649.8, 11923.36],
        [25644.18, 11920.8],
        [25642.86, 11919.11],
        [25640.83, 11923.07],
        [25641.2, 11927.8],
        [25643.35, 11931.48],
        [25646.5, 11933.54],
        [25652.25, 11935.13],
        [25656.93, 11934.8],
        [25663.47, 11932.45],
        [25665.97, 11927.8],
        [25663.76, 11923.03],
        [25660.03, 11918.68]
      ]
    ]
  },
  "properties": {
    "classification": {
      "parentClass": {
        "name": "Positive",
        "colorRGB": -8342656
      },
      "name": "Positive",
      "colorRGB": -10451360
    },
    "isLocked": false,
    "measurements": [
      {
        "name": "Area µm^2",
        "value": 57.955604553222656
      },
      {
        "name": "Length µm",
        "value": 32.26121520996094
      },
      {
        "name": "Circularity",
        "value": 0.6997515559196472
      },
      {
        "name": "Solidity",
        "value": 0.8503648638725281
      },
      {
        "name": "Max diameter µm",
        "value": 11.614229202270508
      },
      {
        "name": "Min diameter µm",
        "value": 7.377708435058594
      },
      {
        "name": "Hematoxylin: Mean",
        "value": 0.19251857697963715
      },
      {
        "name": "Hematoxylin: Median",
        "value": 0.19758310914039612
      },
      {
        "name": "Hematoxylin: Min",
        "value": -0.0068559166975319386
      },
      {
        "name": "Hematoxylin: Max",
        "value": 0.32473286986351013
      },
      {
        "name": "Hematoxylin: Std.Dev.",
        "value": 0.06571684032678604
      },
      {
        "name": "DAB: Mean",
        "value": 0.966644823551178
      },
      {
        "name": "DAB: Median",
        "value": 1.0337783098220825
      },
      {
        "name": "DAB: Min",
        "value": 0.04587873816490173
      },
      {
        "name": "DAB: Max",
        "value": 1.3901169300079346
      },
      {
        "name": "DAB: Std.Dev.",
        "value": 0.24789360165596008
      }
    ]
  }
}